{
    "name": "lb_steg",
    "description": "",
    "dependencies": {
        "core": "*",
        "radio": "*",
        "microphone": "*",
        "neopixel": "github:microsoft/pxt-neopixel#v0.7.5",
        "pxt-kitronik-zip-64": "github:kitronikltd/pxt-kitronik-zip-64#v0.1.4"
    },
    "files": [
        "main.blocks",
        "main.ts",
        "README.md",
        "main.py",
        "custom.ts"
    ],
    "testFiles": [
        "test.ts"
    ],
    "targetVersions": {
        "target": "6.0.25",
        "targetId": "microbit"
    },
    "supportedTargets": [
        "microbit"
    ],
    "preferredEditor": "tsprj"
}
